parquetframe-2.0.0.dist-info/METADATA
parquetframe-2.0.0.dist-info/WHEEL
parquetframe-2.0.0.dist-info/entry_points.txt
parquetframe-2.0.0.dist-info/licenses/LICENSE
parquetframe/__init__.py
parquetframe/_rustic.cpython-312-darwin.so
parquetframe/ai/__init__.py
parquetframe/ai/agent.py
parquetframe/ai/config.py
parquetframe/ai/embeddings.py
parquetframe/ai/enhanced_prompts.py
parquetframe/ai/grounding.py
parquetframe/ai/knowlogy_retriever.py
parquetframe/ai/models.py
parquetframe/ai/prompts.py
parquetframe/ai/rag_pipeline.py
parquetframe/ai/tokenizer.py
parquetframe/ai/vector_store.py
parquetframe/backends/__init__.py
parquetframe/backends/rust_backend.py
parquetframe/benchmark.py
parquetframe/benchmark_rust.py
parquetframe/bio.py
parquetframe/cache.py
parquetframe/cli/__init__.py
parquetframe/cli/commands.py
parquetframe/cli/repl.py
parquetframe/cli/workflow.py
parquetframe/cloud/__init__.py
parquetframe/cloud/config.py
parquetframe/cloud/factory.py
parquetframe/cloud/handlers/azure.py
parquetframe/cloud/handlers/base.py
parquetframe/cloud/handlers/gcp.py
parquetframe/cloud/handlers/s3.py
parquetframe/config.py
parquetframe/core.py
parquetframe/core/__init__.py
parquetframe/core/backend.py
parquetframe/core/base.py
parquetframe/core/execution.py
parquetframe/core/formats.py
parquetframe/core/frame.py
parquetframe/core/heuristics.py
parquetframe/core/metrics.py
parquetframe/core/proxy.py
parquetframe/core/reader.py
parquetframe/core/registry.py
parquetframe/core/rust_io.py
parquetframe/core_legacy.py
parquetframe/dac/__init__.py
parquetframe/dac/dashboard.py
parquetframe/dac/layout.py
parquetframe/dac/parser.py
parquetframe/dac/renderer.py
parquetframe/dac/widgets.py
parquetframe/datacontext/__init__.py
parquetframe/datacontext/database_context.py
parquetframe/datacontext/parquet_context.py
parquetframe/distributed/__init__.py
parquetframe/distributed/dask_ops.py
parquetframe/distributed/ray_ops.py
parquetframe/dpac/__init__.py
parquetframe/dpac/runner.py
parquetframe/engines/__init__.py
parquetframe/engines/dask_engine.py
parquetframe/engines/pandas_engine.py
parquetframe/engines/polars_engine.py
parquetframe-2.0.0.dist-info/RECORD
