Metadata-Version: 2.4
Name: parquetframe
Version: 2.0.0
Classifier: Development Status :: 5 - Production/Stable
Classifier: Intended Audience :: Developers
Classifier: Intended Audience :: Science/Research
Classifier: License :: OSI Approved :: MIT License
Classifier: Operating System :: OS Independent
Classifier: Programming Language :: Python :: 3
Classifier: Programming Language :: Python :: 3.11
Classifier: Programming Language :: Python :: 3.12
Classifier: Programming Language :: Python :: 3.13
Classifier: Programming Language :: Python :: 3.14
Classifier: Topic :: Scientific/Engineering
Classifier: Topic :: Scientific/Engineering :: Bio-Informatics
Classifier: Topic :: Database
Classifier: Topic :: Software Development :: Libraries :: Python Modules
Classifier: Environment :: Console
Classifier: Typing :: Typed
Requires-Dist: pandas>=2.0.0
Requires-Dist: dask[dataframe]>=2024.1.0
Requires-Dist: pyarrow>=10.0.0
Requires-Dist: polars>=0.19.0 ; extra == 'phase2'
Requires-Dist: fastavro>=1.8.0 ; extra == 'phase2'
Requires-Dist: polars>=0.19.0 ; extra == 'engines'
Requires-Dist: pytest>=7.0 ; extra == 'dev'
Requires-Dist: pytest-cov>=4.0 ; extra == 'dev'
Requires-Dist: pytest-mock>=3.10 ; extra == 'dev'
Requires-Dist: pytest-asyncio>=0.23.0 ; extra == 'dev'
Requires-Dist: ruff>=0.1.0 ; extra == 'dev'
Requires-Dist: black>=23.0 ; extra == 'dev'
Requires-Dist: pre-commit>=3.0 ; extra == 'dev'
Requires-Dist: mypy>=1.0 ; extra == 'dev'
Requires-Dist: tox>=4.0 ; extra == 'dev'
Requires-Dist: markdown>=3.0 ; extra == 'dev'
Requires-Dist: mkdocs>=1.5.0 ; extra == 'docs'
Requires-Dist: mkdocs-material>=9.0.0 ; extra == 'docs'
Requires-Dist: mkdocstrings[python]>=0.24.0 ; extra == 'docs'
Requires-Dist: pytest>=7.0 ; extra == 'test'
Requires-Dist: pytest-cov>=4.0 ; extra == 'test'
Requires-Dist: pytest-mock>=3.10 ; extra == 'test'
Requires-Dist: pytest-asyncio>=0.23.0 ; extra == 'test'
Requires-Dist: fastavro>=1.8.0 ; extra == 'test'
Requires-Dist: s3fs>=2023.1.0 ; extra == 'test'
Requires-Dist: click>=8.0 ; extra == 'cli'
Requires-Dist: rich>=13.0 ; extra == 'cli'
Requires-Dist: psutil>=5.8.0 ; extra == 'cli'
Requires-Dist: pyyaml>=6.0 ; extra == 'cli'
Requires-Dist: duckdb>=0.9.0 ; extra == 'cli'
Requires-Dist: polars>=1.33.1 ; extra == 'cli'
Requires-Dist: duckdb>=0.9.0 ; extra == 'sql'
Requires-Dist: sqlalchemy>=2.0.0 ; extra == 'db'
Requires-Dist: bioframe>=0.4.0 ; extra == 'bio'
Requires-Dist: ollama>=0.1.7 ; extra == 'ai'
Requires-Dist: prompt-toolkit>=3.0.0 ; extra == 'ai'
Requires-Dist: datafusion>=33.0.0 ; extra == 'ai'
Requires-Dist: polars>=0.19.0 ; extra == 'all'
Requires-Dist: fastavro>=1.8.0 ; extra == 'all'
Requires-Dist: click>=8.0 ; extra == 'all'
Requires-Dist: rich>=13.0 ; extra == 'all'
Requires-Dist: psutil>=5.8.0 ; extra == 'all'
Requires-Dist: pyyaml>=6.0 ; extra == 'all'
Requires-Dist: duckdb>=0.9.0 ; extra == 'all'
Requires-Dist: sqlalchemy>=2.0.0 ; extra == 'all'
Requires-Dist: bioframe>=0.4.0 ; extra == 'all'
Requires-Dist: ollama>=0.1.7 ; extra == 'all'
Requires-Dist: prompt-toolkit>=3.0.0 ; extra == 'all'
Provides-Extra: phase2
Provides-Extra: engines
Provides-Extra: dev
Provides-Extra: docs
Provides-Extra: test
Provides-Extra: cli
Provides-Extra: sql
Provides-Extra: db
Provides-Extra: bio
Provides-Extra: ai
Provides-Extra: rust
Provides-Extra: all
License-File: LICENSE
Summary: A universal data processing framework with multi-engine support (pandas, Polars, Dask) and multi-format I/O (CSV, JSON, Parquet, ORC, Avro) with intelligent backend selection
Keywords: pandas,polars,dask,parquet,csv,json,orc,avro,dataframe,big-data,multi-engine,sql,duckdb,bioframe,genomics,cli,multi-format,data-science,analytics,bioinformatics,file-format,entity-framework
Author-email: Christopher Murray <lee.christopher.murray@gmail.com>
Requires-Python: >=3.11
Project-URL: Homepage, https://leechristophermurray.github.io/parquetframe/
Project-URL: Documentation, https://leechristophermurray.github.io/parquetframe/
Project-URL: Repository, https://github.com/leechristophermurray/parquetframe.git
Project-URL: Bug Tracker, https://github.com/leechristophermurray/parquetframe/issues
Project-URL: Changelog, https://github.com/leechristophermurray/parquetframe/blob/main/CHANGELOG.md
